README.md
setup.py
financialmodelingprep/__init__.py
financialmodelingprep/calendars.py
financialmodelingprep/company_valuation.py
financialmodelingprep/decorator.py
financialmodelingprep/financialmodelingprep.py
financialmodelingprep/institutional_fund.py
financialmodelingprep/stock_time_series.py
financialmodelingprep/technical_indicators.py
financialmodelingprep.egg-info/PKG-INFO
financialmodelingprep.egg-info/SOURCES.txt
financialmodelingprep.egg-info/dependency_links.txt
financialmodelingprep.egg-info/requires.txt
financialmodelingprep.egg-info/top_level.txt