Metadata-Version: 2.1
Name: financialmodelingprep
Version: 0.0.1
Summary: The unofficial python interface for the financialmodelingprep API
Home-page: https://github.com/JosephCottingham/financialmodelingprep-python.git
Author: Joseph Cottingham | Joseph Conigliari
Author-email: joseph.cottingham@protonmail.com
License: MIT
Platform: UNKNOWN
Classifier: Programming Language :: Python :: 3
Classifier: License :: OSI Approved :: MIT License
Classifier: Operating System :: OS Independent
Requires-Python: >=3.6
